MANIFEST.in
requirements.txt
setup.py
personalizedcancerdiagnosis.egg-info/PKG-INFO
personalizedcancerdiagnosis.egg-info/SOURCES.txt
personalizedcancerdiagnosis.egg-info/dependency_links.txt
personalizedcancerdiagnosis.egg-info/requires.txt
personalizedcancerdiagnosis.egg-info/top_level.txt
regression_model/VERSION
regression_model/__init__.py
regression_model/pipeline.py
regression_model/predict.py
regression_model/train_pipeline.py
regression_model/train_vect_pipeline.py
regression_model/vect_pipeline.py
regression_model/config/__init__.py
regression_model/config/config.py
regression_model/config/logging_config.py
regression_model/datasets/train.csv
regression_model/processing/__init__.py
regression_model/processing/data_management.py
regression_model/processing/errors.py
regression_model/processing/features.py
regression_model/processing/preprocessors.py
regression_model/processing/validation.py
regression_model/processing/vect_preprocessors.py
regression_model/trained_encoders/__init__.py
regression_model/trained_encoders/one_hot_gene.pkl
regression_model/trained_encoders/one_hot_text.pkl
regression_model/trained_encoders/one_hot_variation.pkl
regression_model/trained_encoders/standardscaler.pkl
regression_model/trained_models/__init__.py
regression_model/trained_models/logistic_regression_output_v0.0.1.pkl