Metadata-Version: 2.1
Name: personalizedcancerdiagnosis
Version: 0.0.1
Summary: Logistic Regression model API for prediction of type of cancer mutation based on evidences from text-based clinical literature.
Home-page: https://github.com/Debadri3/Personalized-Cancer-Diagnosis
Author: Debadri Sengupta
Author-email: debadri3@gmail.com
License: BSD 3
Platform: UNKNOWN
Classifier: License :: OSI Approved :: MIT License
Classifier: Programming Language :: Python
Classifier: Programming Language :: Python :: 3
Classifier: Programming Language :: Python :: 3.6
Classifier: Programming Language :: Python :: 3.7
Classifier: Programming Language :: Python :: 3.8
Classifier: Programming Language :: Python :: Implementation :: CPython
Classifier: Programming Language :: Python :: Implementation :: PyPy
Requires-Python: >=3.7.4
